device_scan/__init__.py
device_scan/publish.py
device_scan-0.1.0.dev0.dist-info/entry_points.txt
device_scan-0.1.0.dev0.dist-info/LICENSE
device_scan-0.1.0.dev0.dist-info/WHEEL
device_scan-0.1.0.dev0.dist-info/METADATA
device_scan-0.1.0.dev0.dist-info/RECORD
