Metadata-Version: 2.1
Name: device-scan
Version: 0.1.0.dev0
Summary: Python lib for find devices in own network subnet
Home-page: https://github.com/jedie/device-scan/
License: GPL-3.0-or-later
Keywords: creole,markup,creole2html,html2creole,rest2html,html2rest,html2textile
Author: Jens Diemer
Author-email: device-scan@jensdiemer.de
Requires-Python: >=3.6,<4.0
Classifier: Development Status :: 1 - Planning
Classifier: Environment :: Web Environment
Classifier: Intended Audience :: Developers
Classifier: License :: OSI Approved :: GNU General Public License (GPL)
Classifier: License :: OSI Approved :: GNU General Public License v3 or later (GPLv3+)
Classifier: Operating System :: OS Independent
Classifier: Programming Language :: Python
Classifier: Programming Language :: Python :: 3
Classifier: Programming Language :: Python :: 3.6
Classifier: Programming Language :: Python :: 3.7
Classifier: Programming Language :: Python :: 3.8
Classifier: Programming Language :: Python :: Implementation :: PyPy
Classifier: Topic :: Documentation
Classifier: Topic :: Internet :: WWW/HTTP :: Dynamic Content
Classifier: Topic :: Software Development :: Libraries :: Python Modules
Classifier: Topic :: Utilities
